LICENSE
MANIFEST.in
README.md
VERSION
setup.py
bin/gen_names.bat
gen_names/__init__.py
gen_names/gen_names.py
names_gen.egg-info/PKG-INFO
names_gen.egg-info/SOURCES.txt
names_gen.egg-info/dependency_links.txt
names_gen.egg-info/requires.txt
names_gen.egg-info/top_level.txt