Metadata-Version: 2.1
Name: names-gen
Version: 1.0.4
Summary: Generate random names with lenght
Home-page: https://github.com/treyhunner/names
Author: Michal Kopys
Author-email: mikopys@gmail.com
License: UNKNOWN
Keywords: random names
Platform: UNKNOWN
